{
    "review": {
        "id": 1,
        "contents": "꽤 길고 박시해요. 딱 만졌을 때 면은 도톰하니 되게 질이 좋아보여요 기장이 길어서 바지 안에 넣어입기에는 좀 귀찮고 모델사진처럼 치마에 넣어입으니까 편하고 좋네요 초록색 레터링에 반해서 좀 비싸도 사봤는데 만족합니다 여름에 두루두루 잘 입을 수 있을 것 같아요\r\n다만 트임을 이용해서 앞만 넣고 입는건 뒤에 남는 기장 때문에 개인적으로 좀 애매한것 같아요\r\n꽤 길고 박시해요. 딱 만졌을 때 면은 도톰하니 되게 질이 좋아보여요 기장이 길어서 바지 안에 넣어입기에는 좀 귀찮고 모델사진처럼 치마에 넣어입으니까 편하고 좋네요 초록색 레터링에 반해서 좀 비싸도 사봤는데 만족합니다 여름에 두루두루 잘 입을 수 있을 것 같아요\r\n다만 트임을 이용해서 앞만 넣고 입는건 뒤에 남는 기장 때문에 개인적으로 좀 애매한것 같아요\r\n꽤 길고 박시해요. 딱 만졌을 때 면은 도톰하니 되게 질이 좋아보여요 기장이 길어서 바지 안에 넣어입기에는 좀 귀찮고 모델사진처럼 치마에 넣어입으니까 편하고 좋네요 초록색 레터링에 반해서 좀 비싸도 사봤는데 만족합니다 여름에 두루두루 잘 입을 수 있을 것 같아요 \r\n다만 트임을 이용해서 앞만 넣고 입는건 뒤에 남는 기장 때문에 개인적으로 좀 애매한것 같아요",
        "rate": 3,
        "templates": [
            {
                "id": 7,
                "title": "사이즈",
                "details": [
                    {
                        "id": 14,
                        "label": "예상보다 커요"
                    }
                ]
            }
        ],
        "selected_templates": [
            {
                "template_id": 7,
                "detail_id": 16
            }
        ],
        "height": 150,
        "weight": 60,
        "shoes_size": 230,
        "image_urls": [
            "https://img.nstationmall.com/mall//display/mmon-templates/1/1/219/pc_image_1.jpg?ut=2022-05-30%2017:25:53"
        ]
    }
}